pywave/__init__.py
pywave/abc.py
pywave/backoff.py
pywave/enums.py
pywave/errors.py
pywave/filters.py
pywave/player.py
pywave/pool.py
pywave/queue.py
pywave/stats.py
pywave/tracks.py
pywave/utils.py
pywave/websocket.py
pywave/ext/spotify/__init__.py
pywave/types/queue.py
pywavee-1.5.dist-info/LICENSE
pywavee-1.5.dist-info/METADATA
pywavee-1.5.dist-info/WHEEL
pywavee-1.5.dist-info/top_level.txt
pywavee-1.5.dist-info/RECORD
