Metadata-Version: 2.1
Name: pywavee
Version: 1.5
Summary: A  robust and powerful Lavalink wrapper for py-cord and derivatives.
Home-page: https://github.com/timoo4devv/pywave/
Author: PythonistaGuild, EvieePy, Timo
License: MIT
Classifier: License :: OSI Approved :: MIT License
Classifier: Intended Audience :: Developers
Classifier: Natural Language :: English
Classifier: Operating System :: OS Independent
Classifier: Programming Language :: Python :: 3.8
Classifier: Programming Language :: Python :: 3.9
Classifier: Programming Language :: Python :: 3.10
Classifier: Programming Language :: Python :: 3.11
Classifier: Programming Language :: Python :: 3.12
Classifier: Topic :: Internet
Classifier: Topic :: Software Development :: Libraries
Classifier: Topic :: Software Development :: Libraries :: Python Modules
Classifier: Topic :: Utilities
License-File: LICENSE
Requires-Dist: aiohttp
Requires-Dist: py-cord
